{
    "first": [
        {
            "animeType": [
                {
                    "route": "anime://classify.anime.app?partUrl=%2F70%2F&classifyTitle=%E6%A0%A1%E5%9B%AD",
                    "title": "校园",
                    "url": "http://xxx.xxx.xxx/70/"
                },
                {
                    "route": "anime://classify.anime.app?partUrl=%2F119%2F&classifyTitle=%E5%90%B8%E8%A1%80%E9%AC%BC",
                    "title": "吸血鬼",
                    "url": "http://xxx.xxx.xxx/119/"
                },
                {
                    "route": "anime://classify.anime.app?partUrl=%2F99%2F&classifyTitle=%E5%90%8E%E5%AE%AB",
                    "title": "后宫",
                    "url": "http://xxx.xxx.xxx/99/"
                }
            ],
            "cover": {
                "referer": "http://xxx.xxx.xxx/201901/",
                "actionUrl": "",
                "url": "http://xxx.xxx.xxx/comic/acg/2018/10/01/201810010301.jpg"
            },
            "describe": "动漫简介：「第四真祖」是只存在于传说中的世界最强之吸血鬼。而这位驾驭12眷兽、散播灾难的幻之吸血鬼据说在日本出现了。为了监视并抹杀这位「第四真祖」，政府所属的狮子王机关决定派遣攻魔师「剑巫」完成任务。而不知为...",
            "episode": "10集全",
            "route": "/show/4314.html",
            "title": "噬血狂袭第三季",
            "url": "http://xxx.xxx.xxx/show/4314.html"
        },
        {
            "animeType": [
                {
                    "route": "anime://classify.anime.app?partUrl=%2F60%2F&classifyTitle=%E5%A5%87%E5%B9%BB",
                    "title": "奇幻",
                    "url": "http://xxx.xxx.xxx/60/"
                },
                {
                    "route": "anime://classify.anime.app?partUrl=%2F61%2F&classifyTitle=%E5%86%92%E9%99%A9",
                    "title": "冒险",
                    "url": "http://xxx.xxx.xxx/61/"
                }
            ],
            "cover": {
                "referer": "http://xxx.xxx.xxx/201901/",
                "actionUrl": "",
                "url": "http://xxx.xxx.xxx/comic/acg/2019/01/01/201901011138.jpg"
            },
            "describe": "动漫简介：极为平凡的御宅族大学生·岩谷尚文，受到在图书馆发现的一本书所引导，被召唤到了异世界。他被赋予的使命，是作为装备着剑、枪、弓、盾的四圣勇者之一“盾之勇者”，驱逐给世界带来混沌的灾害“波”。因为大冒险...",
            "episode": "25集全",
            "route": "/show/4331.html",
            "title": "盾之勇者成名录",
            "url": "http://xxx.xxx.xxx/show/4331.html"
        },
        {
            "animeType": [
                {
                    "route": "anime://classify.anime.app?partUrl=%2F61%2F&classifyTitle=%E5%86%92%E9%99%A9",
                    "title": "冒险",
                    "url": "http://xxx.xxx.xxx/61/"
                },
                {
                    "route": "anime://classify.anime.app?partUrl=%2F73%2F&classifyTitle=%E9%AD%94%E6%B3%95",
                    "title": "魔法",
                    "url": "http://xxx.xxx.xxx/73/"
                },
                {
                    "route": "anime://classify.anime.app?partUrl=%2F66%2F&classifyTitle=%E7%83%AD%E8%A1%80",
                    "title": "热血",
                    "url": "http://xxx.xxx.xxx/66/"
                }
            ],
            "cover": {
                "referer": "http://xxx.xxx.xxx/201901/",
                "actionUrl": "",
                "url": "http://xxx.xxx.xxx/comic/acg/2019/01/01/201901011151.jpg"
            },
            "describe": "动漫简介：时为战国。醍醐之国主景光，在某所寺院的大堂中，向12尊鬼神像许愿领土繁荣。作为交换而诞生的景光之后嗣，身体各处都有所欠缺，被视作不祥之子而抛弃到河川之中。时光流逝，鬼神实现了与景光的约定，国家迎来了...",
            "episode": "24集全",
            "route": "/show/4344.html",
            "title": "多罗罗",
            "url": "http://xxx.xxx.xxx/show/4344.html"
        },
        {
            "animeType": [
                {
                    "route": "anime://classify.anime.app?partUrl=%2F60%2F&classifyTitle=%E5%A5%87%E5%B9%BB",
                    "title": "奇幻",
                    "url": "http://xxx.xxx.xxx/60/"
                },
                {
                    "route": "anime://classify.anime.app?partUrl=%2F140%2F&classifyTitle=%E6%AD%8C%E8%88%9E",
                    "title": "歌舞",
                    "url": "http://xxx.xxx.xxx/140/"
                }
            ],
            "cover": {
                "referer": "http://xxx.xxx.xxx/201901/",
                "actionUrl": "",
                "url": "http://xxx.xxx.xxx/comic/acg/2019/04/03/20190403041925982.jpg"
            },
            "describe": "动漫简介：将遗弃在森林里的钢琴当做玩具而成长的主人公一之濑海，通过与曾被称作天才钢琴家的阿字野壮介以及拥有伟大钢琴家父亲的雨宫修平等人相遇，使自己的钢琴才能开花，并在之后挑战肖邦钢琴赛——描写的就是这样一个...",
            "episode": "12集全",
            "route": "/show/4347.html",
            "title": "钢琴之森第二季",
            "url": "http://xxx.xxx.xxx/show/4347.html"
        },
        {
            "animeType": [
                {
                    "route": "anime://classify.anime.app?partUrl=%2F140%2F&classifyTitle=%E6%AD%8C%E8%88%9E",
                    "title": "歌舞",
                    "url": "http://xxx.xxx.xxx/140/"
                },
                {
                    "route": "anime://classify.anime.app?partUrl=%2F290%2F&classifyTitle=%E5%A5%B3%E6%80%A7%E5%90%91",
                    "title": "女性向",
                    "url": "http://xxx.xxx.xxx/290/"
                }
            ],
            "cover": {
                "referer": "http://xxx.xxx.xxx/201901/",
                "actionUrl": "",
                "url": "http://xxx.xxx.xxx/comic/acg/2019/01/01/201901011171.jpg"
            },
            "describe": "动漫简介：W z确定是一部女性向动画，这次是邀请到专业的 DJ RENA 来为动画的影像和音乐担任监修，在音乐方面有总计将近 30 位音乐人或者组合参加，而且在视觉海报上也是突出主角打碟的形象，看来这男主角应该和 D...",
            "episode": "14集全",
            "route": "/show/4364.html",
            "title": "W'z",
            "url": "http://xxx.xxx.xxx/show/4364.html"
        },
        {
            "animeType": [
                {
                    "route": "anime://classify.anime.app?partUrl=%2F75%2F&classifyTitle=%E7%A7%91%E5%B9%BB",
                    "title": "科幻",
                    "url": "http://xxx.xxx.xxx/75/"
                },
                {
                    "route": "anime://classify.anime.app?partUrl=%2F81%2F&classifyTitle=%E6%9C%BA%E6%88%98",
                    "title": "机战",
                    "url": "http://xxx.xxx.xxx/81/"
                }
            ],
            "cover": {
                "referer": "http://xxx.xxx.xxx/201901/",
                "actionUrl": "",
                "url": "http://xxx.xxx.xxx/comic/acg/2019/01/01/201901011163.jpg"
            },
            "describe": "动漫简介：突然出现的神祕飞翔体“灾”，压倒了人类的航空战力。 为了与之对抗而开发的，便是对现有机体进行改造，被称为“子体”的兵器。负责操控的则是名为“阿尼玛”的操纵机构。它──竟拥有少女的外表。 与鸣谷慧相遇...",
            "episode": "12集全",
            "route": "/show/4356.html",
            "title": "飞翔吧! 战机少女",
            "url": "http://xxx.xxx.xxx/show/4356.html"
        },
        {
            "animeType": [
                {
                    "route": "anime://classify.anime.app?partUrl=%2F139%2F&classifyTitle=%E5%8A%A8%E4%BD%9C",
                    "title": "动作",
                    "url": "http://xxx.xxx.xxx/139/"
                },
                {
                    "route": "anime://classify.anime.app?partUrl=%2F75%2F&classifyTitle=%E7%A7%91%E5%B9%BB",
                    "title": "科幻",
                    "url": "http://xxx.xxx.xxx/75/"
                }
            ],
            "cover": {
                "referer": "http://xxx.xxx.xxx/201901/",
                "actionUrl": "",
                "url": "http://xxx.xxx.xxx/comic/acg/2019/01/01/201901011174.jpg"
            },
            "describe": "动漫简介：初代奥特曼世界观初代奥特曼与宇宙恐龙杰顿战斗结束后 初代返回了故乡M78星云光之国 解除了与科学特搜队队员早田的同步融合 早田作为初代奥特曼在地球的人类融合体 过着失去了奥特曼相关记忆后的平静生活 偶...",
            "episode": "13集全",
            "route": "/show/4367.html",
            "title": "机动奥特曼日语版",
            "url": "http://xxx.xxx.xxx/show/4367.html"
        },
        {
            "animeType": [
                {
                    "route": "anime://classify.anime.app?partUrl=%2F72%2F&classifyTitle=%E7%BE%8E%E5%B0%91%E5%A5%B3",
                    "title": "美少女",
                    "url": "http://xxx.xxx.xxx/72/"
                },
                {
                    "route": "anime://classify.anime.app?partUrl=%2F67%2F&classifyTitle=%E6%90%9E%E7%AC%91",
                    "title": "搞笑",
                    "url": "http://xxx.xxx.xxx/67/"
                },
                {
                    "route": "anime://classify.anime.app?partUrl=%2F151%2F&classifyTitle=%E6%B3%A1%E9%9D%A2%E7%95%AA",
                    "title": "泡面番",
                    "url": "http://xxx.xxx.xxx/151/"
                }
            ],
            "cover": {
                "referer": "http://xxx.xxx.xxx/201901/",
                "actionUrl": "",
                "url": "http://xxx.xxx.xxx/comic/acg/2019/04/02/20190402104805262.jpg"
            },
            "describe": "动漫简介：建造于这个世界某处的超巨大综合动物园“Japari Park”。那里的动物们有着可以变化成人类身姿的现象。不知何时开始用朋友来呼唤着彼此的动物们在Park里和平的生活着。有一天薮猫和她朋友在森林中与人类的小孩相...",
            "episode": "12集全",
            "route": "/show/4359.html",
            "title": "兽娘动物园第二季",
            "url": "http://xxx.xxx.xxx/show/4359.html"
        },
        {
            "animeType": [
                {
                    "route": "anime://classify.anime.app?partUrl=%2F60%2F&classifyTitle=%E5%A5%87%E5%B9%BB",
                    "title": "奇幻",
                    "url": "http://xxx.xxx.xxx/60/"
                },
                {
                    "route": "anime://classify.anime.app?partUrl=%2F83%2F&classifyTitle=%E7%A5%9E%E9%AD%94",
                    "title": "神魔",
                    "url": "http://xxx.xxx.xxx/83/"
                },
                {
                    "route": "anime://classify.anime.app?partUrl=%2F70%2F&classifyTitle=%E6%A0%A1%E5%9B%AD",
                    "title": "校园",
                    "url": "http://xxx.xxx.xxx/70/"
                }
            ],
            "cover": {
                "referer": "http://xxx.xxx.xxx/201901/",
                "actionUrl": "",
                "url": "http://xxx.xxx.xxx/comic/acg/2019/01/01/201901011173.jpg"
            },
            "describe": "动漫简介：想要过普通生活的中学2年生·影山茂夫，通称“龙套”。有着一瞬间就会混杂在人群中的不起眼外表的他，实际上拥有比任何人都要强力的超能力……。这样的龙套与周围人们之间的青春与恋爱，静静地累积直至爆发的种种...",
            "episode": "13集全",
            "route": "/show/4366.html",
            "title": "灵能百分百第二季",
            "url": "http://xxx.xxx.xxx/show/4366.html"
        },
        {
            "animeType": [
                {
                    "route": "anime://classify.anime.app?partUrl=%2F81%2F&classifyTitle=%E6%9C%BA%E6%88%98",
                    "title": "机战",
                    "url": "http://xxx.xxx.xxx/81/"
                },
                {
                    "route": "anime://classify.anime.app?partUrl=%2F75%2F&classifyTitle=%E7%A7%91%E5%B9%BB",
                    "title": "科幻",
                    "url": "http://xxx.xxx.xxx/75/"
                },
                {
                    "route": "anime://classify.anime.app?partUrl=%2F85%2F&classifyTitle=%E5%8A%B1%E5%BF%97",
                    "title": "励志",
                    "url": "http://xxx.xxx.xxx/85/"
                }
            ],
            "cover": {
                "referer": "http://xxx.xxx.xxx/201901/",
                "actionUrl": "",
                "url": "http://xxx.xxx.xxx/comic/acg/2019/01/01/201901011167.jpg"
            },
            "describe": "动漫简介：在一片荒野的广阔世界，突然从天空降落下各种各样的物品。它们急剧地改变了人们的生活，尤其是飞机带来的影响最大。那之后，世界的潮流转移到了天空。 时光流逝—— 被人们雇佣的保镖部队“寿飞行队”， 与严厉...",
            "episode": "12集全",
            "route": "/show/4360.html",
            "title": "荒野的寿飞行队",
            "url": "http://xxx.xxx.xxx/show/4360.html"
        },
        {
            "animeType": [
                {
                    "route": "anime://classify.anime.app?partUrl=%2F60%2F&classifyTitle=%E5%A5%87%E5%B9%BB",
                    "title": "奇幻",
                    "url": "http://xxx.xxx.xxx/60/"
                },
                {
                    "route": "anime://classify.anime.app?partUrl=%2F180%2F&classifyTitle=%E5%96%9C%E5%89%A7",
                    "title": "喜剧",
                    "url": "http://xxx.xxx.xxx/180/"
                },
                {
                    "route": "anime://classify.anime.app?partUrl=%2F359%2F&classifyTitle=%E6%97%A5%E5%B8%B8",
                    "title": "日常",
                    "url": "http://xxx.xxx.xxx/359/"
                }
            ],
            "cover": {
                "referer": "http://xxx.xxx.xxx/201901/",
                "actionUrl": "",
                "url": "http://xxx.xxx.xxx/comic/acg/2019/01/01/201901011161.jpg"
            },
            "describe": "动漫简介：——尤莉娅·夏尔戴特，无职业♪ 人们与怪物共存的剑与魔法的大陆“纳拉尔岛”。那里曾经存在恐怖的“魔王”。很久很久以前，初代勇者打倒了出现在纳拉尔岛的魔王——从那以后，魔王在各种时代不断地复活，同时与...",
            "episode": "12集全",
            "route": "/show/4354.html",
            "title": "Endro!",
            "url": "http://xxx.xxx.xxx/show/4354.html"
        },
        {
            "animeType": [
                {
                    "route": "anime://classify.anime.app?partUrl=%2F70%2F&classifyTitle=%E6%A0%A1%E5%9B%AD",
                    "title": "校园",
                    "url": "http://xxx.xxx.xxx/70/"
                },
                {
                    "route": "anime://classify.anime.app?partUrl=%2F91%2F&classifyTitle=%E6%81%8B%E7%88%B1",
                    "title": "恋爱",
                    "url": "http://xxx.xxx.xxx/91/"
                }
            ],
            "cover": {
                "referer": "http://xxx.xxx.xxx/201901/",
                "actionUrl": "",
                "url": "http://xxx.xxx.xxx/comic/acg/2019/01/01/201901011162.jpg"
            },
            "describe": "动漫简介：家庭背景与人品都很棒！！一大群有前途的秀才所聚集的秀知院学园！！在那里的学生会相遇的副会长·四宫辉夜与会长·白银御行原本应该是彼此受到了对方吸引…但想不到都过半年了却仍然什么事情也没发生！！最麻烦...",
            "episode": "12集全",
            "route": "/show/4355.html",
            "title": "辉夜姬想让人告白 天才们的恋爱头脑战",
            "url": "http://xxx.xxx.xxx/show/4355.html"
        },
        {
            "animeType": [
                {
                    "route": "anime://classify.anime.app?partUrl=%2F72%2F&classifyTitle=%E7%BE%8E%E5%B0%91%E5%A5%B3",
                    "title": "美少女",
                    "url": "http://xxx.xxx.xxx/72/"
                },
                {
                    "route": "anime://classify.anime.app?partUrl=%2F91%2F&classifyTitle=%E6%81%8B%E7%88%B1",
                    "title": "恋爱",
                    "url": "http://xxx.xxx.xxx/91/"
                },
                {
                    "route": "anime://classify.anime.app?partUrl=%2F77%2F&classifyTitle=%E5%89%A7%E6%83%85",
                    "title": "剧情",
                    "url": "http://xxx.xxx.xxx/77/"
                }
            ],
            "cover": {
                "referer": "http://xxx.xxx.xxx/201901/",
                "actionUrl": "",
                "url": "http://xxx.xxx.xxx/comic/acg/2019/01/01/201901011143.jpg"
            },
            "describe": "动漫简介：五个人鱼少女的日常故事。",
            "episode": "完结12",
            "route": "/show/4336.html",
            "title": "百慕大三角～Colorful Pastrale～",
            "url": "http://xxx.xxx.xxx/show/4336.html"
        },
        {
            "animeType": [
                {
                    "route": "anime://classify.anime.app?partUrl=%2F83%2F&classifyTitle=%E7%A5%9E%E9%AD%94",
                    "title": "神魔",
                    "url": "http://xxx.xxx.xxx/83/"
                },
                {
                    "route": "anime://classify.anime.app?partUrl=%2F60%2F&classifyTitle=%E5%A5%87%E5%B9%BB",
                    "title": "奇幻",
                    "url": "http://xxx.xxx.xxx/60/"
                },
                {
                    "route": "anime://classify.anime.app?partUrl=%2F70%2F&classifyTitle=%E6%A0%A1%E5%9B%AD",
                    "title": "校园",
                    "url": "http://xxx.xxx.xxx/70/"
                }
            ],
            "cover": {
                "referer": "http://xxx.xxx.xxx/201901/",
                "actionUrl": "",
                "url": "http://xxx.xxx.xxx/comic/acg/2019/01/01/201901011155.jpg"
            },
            "describe": "动漫简介：所谓的“除妖”，即是把由于某些缘由而从原本应在的“隐世”来到“现世”停留的妖怪们送回“隐世”这一工作。某天，被妖怪附体的高中生·芦屋花绘，依靠偶然发现的联络方式，来到了专门除妖的物怪庵，在那里的是...",
            "episode": "13集全",
            "route": "/show/4348.html",
            "title": "忧郁的物怪庵第二季",
            "url": "http://xxx.xxx.xxx/show/4348.html"
        },
        {
            "animeType": [
                {
                    "route": "anime://classify.anime.app?partUrl=%2F73%2F&classifyTitle=%E9%AD%94%E6%B3%95",
                    "title": "魔法",
                    "url": "http://xxx.xxx.xxx/73/"
                },
                {
                    "route": "anime://classify.anime.app?partUrl=%2F149%2F&classifyTitle=%E6%88%98%E6%96%97",
                    "title": "战斗",
                    "url": "http://xxx.xxx.xxx/149/"
                }
            ],
            "cover": {
                "referer": "http://xxx.xxx.xxx/201901/",
                "actionUrl": "",
                "url": "http://xxx.xxx.xxx/comic/acg/2019/01/01/201901011158.jpg"
            },
            "describe": "动漫简介：传说。神话。魔法——随着科学的发展而被遗忘的另一个世界。 21世纪，人类终于实现了与其他的智慧生命体的接触。但是，这一相遇却并非幸福之物。从地冥界侵入地面的怪物，将大多数现代兵器无效化，人类的命运如同...",
            "episode": "12集全",
            "route": "/show/4351.html",
            "title": "魔法少女特殊战明日香",
            "url": "http://xxx.xxx.xxx/show/4351.html"
        },
        {
            "animeType": [
                {
                    "route": "anime://classify.anime.app?partUrl=%2F77%2F&classifyTitle=%E5%89%A7%E6%83%85",
                    "title": "剧情",
                    "url": "http://xxx.xxx.xxx/77/"
                },
                {
                    "route": "anime://classify.anime.app?partUrl=%2F85%2F&classifyTitle=%E5%8A%B1%E5%BF%97",
                    "title": "励志",
                    "url": "http://xxx.xxx.xxx/85/"
                }
            ],
            "cover": {
                "referer": "http://xxx.xxx.xxx/201901/",
                "actionUrl": "",
                "url": "http://xxx.xxx.xxx/comic/acg/2019/01/01/201901011153.jpg"
            },
            "describe": "动漫简介：在业界大牌唱片公司“犍陀罗音乐”，以A&R身份就职的主人公·澄空翼。 她和所负责的偶像组合“B-PROJECT”的成员们一同，跨越各种麻烦和突发事件，梦寐以求的JAPAN Dream Live也获得大成功！ 向下一个舞台进发...",
            "episode": "12集全",
            "route": "/show/4346.html",
            "title": "B-PROJECT第二季",
            "url": "http://xxx.xxx.xxx/show/4346.html"
        },
        {
            "animeType": [
                {
                    "route": "anime://classify.anime.app?partUrl=%2F91%2F&classifyTitle=%E6%81%8B%E7%88%B1",
                    "title": "恋爱",
                    "url": "http://xxx.xxx.xxx/91/"
                },
                {
                    "route": "anime://classify.anime.app?partUrl=%2F77%2F&classifyTitle=%E5%89%A7%E6%83%85",
                    "title": "剧情",
                    "url": "http://xxx.xxx.xxx/77/"
                }
            ],
            "cover": {
                "referer": "http://xxx.xxx.xxx/201901/",
                "actionUrl": "",
                "url": "http://xxx.xxx.xxx/comic/acg/2019/01/01/201901011150.jpg"
            },
            "describe": "动漫简介：幼年丧母的高中男生・藤井夏生，默默暗恋着高中老师・橘阳菜。 无法实现的思念涌入心中，突然被邀请参加联谊的夏生，与在那里遇到的橘瑠衣一起进行了首次体验。 这时，父亲打算再婚。作为父亲再婚对象出现在夏生...",
            "episode": "12集全",
            "route": "/show/4343.html",
            "title": "家有女友",
            "url": "http://xxx.xxx.xxx/show/4343.html"
        },
        {
            "animeType": [
                {
                    "route": "anime://classify.anime.app?partUrl=%2F91%2F&classifyTitle=%E6%81%8B%E7%88%B1",
                    "title": "恋爱",
                    "url": "http://xxx.xxx.xxx/91/"
                },
                {
                    "route": "anime://classify.anime.app?partUrl=%2F99%2F&classifyTitle=%E5%90%8E%E5%AE%AB",
                    "title": "后宫",
                    "url": "http://xxx.xxx.xxx/99/"
                },
                {
                    "route": "anime://classify.anime.app?partUrl=%2F70%2F&classifyTitle=%E6%A0%A1%E5%9B%AD",
                    "title": "校园",
                    "url": "http://xxx.xxx.xxx/70/"
                },
                {
                    "route": "anime://classify.anime.app?partUrl=%2F75%2F&classifyTitle=%E7%A7%91%E5%B9%BB",
                    "title": "科幻",
                    "url": "http://xxx.xxx.xxx/75/"
                }
            ],
            "cover": {
                "referer": "http://xxx.xxx.xxx/201901/",
                "actionUrl": "",
                "url": "http://xxx.xxx.xxx/comic/acg/2019/01/01/201901011172.jpg"
            },
            "describe": "动漫简介：人类遭遇了名为“空间震”的新型灾害。震荡空间、将一切破坏殆尽的这一灾厄，是由于存在于临界的精灵出现这个世界上时而发生的。为了阻止空间震，使人类免受灾厄而必须采取的措施，是使用武力歼灭精灵，或者是—...",
            "episode": "12集全",
            "route": "/show/4365.html",
            "title": "约会大作战第三季",
            "url": "http://xxx.xxx.xxx/show/4365.html"
        },
        {
            "animeType": [
                {
                    "route": "anime://classify.anime.app?partUrl=%2F77%2F&classifyTitle=%E5%89%A7%E6%83%85",
                    "title": "剧情",
                    "url": "http://xxx.xxx.xxx/77/"
                }
            ],
            "cover": {
                "referer": "http://xxx.xxx.xxx/201901/",
                "actionUrl": "",
                "url": "http://xxx.xxx.xxx/comic/acg/2019/01/01/201901011156.jpg"
            },
            "describe": "动漫简介：少女宫下藤花，当她察觉到“世界之敌”的时候便会诞生出另一个名为“不吉波普”的人格。围绕着各种奇怪的事件，少年与少女们的故事慢慢展开了",
            "episode": "18集全",
            "route": "/show/4349.html",
            "title": "不吉波普不笑",
            "url": "http://xxx.xxx.xxx/show/4349.html"
        },
        {
            "animeType": [
                {
                    "route": "anime://classify.anime.app?partUrl=%2F61%2F&classifyTitle=%E5%86%92%E9%99%A9",
                    "title": "冒险",
                    "url": "http://xxx.xxx.xxx/61/"
                }
            ],
            "cover": {
                "referer": "http://xxx.xxx.xxx/201901/",
                "actionUrl": "",
                "url": "http://xxx.xxx.xxx/comic/acg/2019/01/01/201901011164.jpg"
            },
            "describe": "动漫简介：人们从出生开始就被付与了一本书。从生到死按照“命运之书”记载的脚本生存下去的宿命。在此之中，持有空白脚本的“空白之书”出生的艾克斯，与同样拥有“空白之书”的同伴们相遇，踏上了寻找自己使命的旅程。这...",
            "episode": "12集全",
            "route": "/show/4357.html",
            "title": "格林笔记",
            "url": "http://xxx.xxx.xxx/show/4357.html"
        },
        {
            "animeType": [
                {
                    "route": "anime://classify.anime.app?partUrl=%2F139%2F&classifyTitle=%E5%8A%A8%E4%BD%9C",
                    "title": "动作",
                    "url": "http://xxx.xxx.xxx/139/"
                },
                {
                    "route": "anime://classify.anime.app?partUrl=%2F75%2F&classifyTitle=%E7%A7%91%E5%B9%BB",
                    "title": "科幻",
                    "url": "http://xxx.xxx.xxx/75/"
                },
                {
                    "route": "anime://classify.anime.app?partUrl=%2F149%2F&classifyTitle=%E6%88%98%E6%96%97",
                    "title": "战斗",
                    "url": "http://xxx.xxx.xxx/149/"
                }
            ],
            "cover": {
                "referer": "http://xxx.xxx.xxx/201901/",
                "actionUrl": "",
                "url": "http://xxx.xxx.xxx/comic/acg/2019/01/01/201901011165.jpg"
            },
            "describe": "动漫简介：以末日废土世界，以被红色的雾所覆盖的世界为舞台，讲述与被称作“虫”的异形怪物战斗的少女们的故事——",
            "episode": "12集全",
            "route": "/show/4358.html",
            "title": "凯美瑞之草",
            "url": "http://xxx.xxx.xxx/show/4358.html"
        },
        {
            "animeType": [
                {
                    "route": "anime://classify.anime.app?partUrl=%2F142%2F&classifyTitle=%E6%82%AC%E7%96%91",
                    "title": "悬疑",
                    "url": "http://xxx.xxx.xxx/142/"
                },
                {
                    "route": "anime://classify.anime.app?partUrl=%2F75%2F&classifyTitle=%E7%A7%91%E5%B9%BB",
                    "title": "科幻",
                    "url": "http://xxx.xxx.xxx/75/"
                },
                {
                    "route": "anime://classify.anime.app?partUrl=%2F61%2F&classifyTitle=%E5%86%92%E9%99%A9",
                    "title": "冒险",
                    "url": "http://xxx.xxx.xxx/61/"
                }
            ],
            "cover": {
                "referer": "http://xxx.xxx.xxx/201901/",
                "actionUrl": "",
                "url": "http://xxx.xxx.xxx/comic/acg/2019/01/01/201901011159.jpg"
            },
            "describe": "动漫简介：仰慕的母亲并非亲生母亲。一起生活的他们并非兄弟。 Grace=Field House是没有父母的孩子们居住的地方。虽然没有血缘关系，但妈妈和38个兄弟都度过了幸福的每一天，这是不可替代的家。 但是，他们的日常在某一天...",
            "episode": "12集全",
            "route": "/show/4352.html",
            "title": "约定的梦幻岛",
            "url": "http://xxx.xxx.xxx/show/4352.html"
        },
        {
            "animeType": [
                {
                    "route": "anime://classify.anime.app?partUrl=%2F91%2F&classifyTitle=%E6%81%8B%E7%88%B1",
                    "title": "恋爱",
                    "url": "http://xxx.xxx.xxx/91/"
                },
                {
                    "route": "anime://classify.anime.app?partUrl=%2F70%2F&classifyTitle=%E6%A0%A1%E5%9B%AD",
                    "title": "校园",
                    "url": "http://xxx.xxx.xxx/70/"
                },
                {
                    "route": "anime://classify.anime.app?partUrl=%2F67%2F&classifyTitle=%E6%90%9E%E7%AC%91",
                    "title": "搞笑",
                    "url": "http://xxx.xxx.xxx/67/"
                }
            ],
            "cover": {
                "referer": "http://xxx.xxx.xxx/201901/",
                "actionUrl": "",
                "url": "http://xxx.xxx.xxx/comic/acg/2019/01/01/201901011168.jpg"
            },
            "describe": "动漫简介：一直过着贫困生活的高中二年级学生·上杉风太郎，找到了一份条件非常好的家庭教师兼职。然而，要教导的学生居然是同级生！而且还是五胞胎！！虽然都是美少女，但同时也是“将要留级”、“讨厌学习”的问题学生们...",
            "episode": "12集全",
            "route": "/show/4361.html",
            "title": "五等分的花嫁",
            "url": "http://xxx.xxx.xxx/show/4361.html"
        },
        {
            "animeType": [
                {
                    "route": "anime://classify.anime.app?partUrl=%2F70%2F&classifyTitle=%E6%A0%A1%E5%9B%AD",
                    "title": "校园",
                    "url": "http://xxx.xxx.xxx/70/"
                },
                {
                    "route": "anime://classify.anime.app?partUrl=%2F84%2F&classifyTitle=%E9%9D%92%E6%98%A5",
                    "title": "青春",
                    "url": "http://xxx.xxx.xxx/84/"
                }
            ],
            "cover": {
                "referer": "http://xxx.xxx.xxx/201901/",
                "actionUrl": "",
                "url": "http://xxx.xxx.xxx/comic/acg/2019/01/01/201901011149.jpg"
            },
            "describe": "动漫简介：不擅长跟人接触，怕生的小说家·朏素晴与被人抛弃，过着残酷的流浪生活的猫。由于偶然的契机下一个人和一只猫开始了同居生活……？ 以人的视角和猫的视角来描绘每天的生活，各自的思绪互相交织在一起。 故事以“...",
            "episode": "12集全",
            "route": "/show/4342.html",
            "title": "同居人时而在腿上、时而在头上",
            "url": "http://xxx.xxx.xxx/show/4342.html"
        },
        {
            "animeType": [
                {
                    "route": "anime://classify.anime.app?partUrl=%2F72%2F&classifyTitle=%E7%BE%8E%E5%B0%91%E5%A5%B3",
                    "title": "美少女",
                    "url": "http://xxx.xxx.xxx/72/"
                },
                {
                    "route": "anime://classify.anime.app?partUrl=%2F140%2F&classifyTitle=%E6%AD%8C%E8%88%9E",
                    "title": "歌舞",
                    "url": "http://xxx.xxx.xxx/140/"
                },
                {
                    "route": "anime://classify.anime.app?partUrl=%2F62%2F&classifyTitle=%E7%AB%9E%E6%8A%80",
                    "title": "竞技",
                    "url": "http://xxx.xxx.xxx/62/"
                },
                {
                    "route": "anime://classify.anime.app?partUrl=%2F85%2F&classifyTitle=%E5%8A%B1%E5%BF%97",
                    "title": "励志",
                    "url": "http://xxx.xxx.xxx/85/"
                }
            ],
            "cover": {
                "referer": "http://xxx.xxx.xxx/201901/",
                "actionUrl": "",
                "url": "http://xxx.xxx.xxx/comic/acg/2019/01/01/201901011152.jpg"
            },
            "describe": "动漫简介：升上高中二年级的香澄等Poppin \"Party成员，不论是在学生会还是在家帮忙，不论是补习还是打工都十分繁忙。 五人在一起的时间逐渐减少，在作为据点的仓库也难以集合。 在...",
            "episode": "13集全",
            "route": "/show/4345.html",
            "title": "BanG Dream!第二季",
            "url": "http://xxx.xxx.xxx/show/4345.html"
        },
        {
            "animeType": [
                {
                    "route": "anime://classify.anime.app?partUrl=%2F67%2F&classifyTitle=%E6%90%9E%E7%AC%91",
                    "title": "搞笑",
                    "url": "http://xxx.xxx.xxx/67/"
                }
            ],
            "cover": {
                "referer": "http://xxx.xxx.xxx/201901/",
                "actionUrl": "",
                "url": "http://xxx.xxx.xxx/comic/acg/2019/01/01/201901011144.jpg"
            },
            "describe": "动漫简介：在家中总是不穿衣服的主人公江古田是一名自由职业者，她白天时是派遣员工，偶尔也会接模特儿的工作。有着极度开放观念的江古田与周遭朋友之间发生了许多有趣的日常故事。",
            "episode": "12集全",
            "route": "/show/4337.html",
            "title": "临死！！江古田",
            "url": "http://xxx.xxx.xxx/show/4337.html"
        },
        {
            "animeType": [
                {
                    "route": "anime://classify.anime.app?partUrl=%2F91%2F&classifyTitle=%E6%81%8B%E7%88%B1",
                    "title": "恋爱",
                    "url": "http://xxx.xxx.xxx/91/"
                },
                {
                    "route": "anime://classify.anime.app?partUrl=%2F77%2F&classifyTitle=%E5%89%A7%E6%83%85",
                    "title": "剧情",
                    "url": "http://xxx.xxx.xxx/77/"
                }
            ],
            "cover": {
                "referer": "http://xxx.xxx.xxx/201901/",
                "actionUrl": "",
                "url": "http://xxx.xxx.xxx/comic/acg/2019/01/01/201901011136.jpg"
            },
            "describe": "动漫简介：非常普通的女高中生主人公在一个红色满月之夜，遇见了一位自称是“魔术师”查理的人相遇。借助查理的手穿越到了明治时代。在这里，存在着很多奇怪的东西，这就是明治时代的“东京”。在查理的引导下，到达了鹿鸣...",
            "episode": "12集全",
            "route": "/show/4329.html",
            "title": "明治东京恋伽",
            "url": "http://xxx.xxx.xxx/show/4329.html"
        },
        {
            "animeType": [
                {
                    "route": "anime://classify.anime.app?partUrl=%2F145%2F&classifyTitle=%E8%81%8C%E5%9C%BA",
                    "title": "职场",
                    "url": "http://xxx.xxx.xxx/145/"
                },
                {
                    "route": "anime://classify.anime.app?partUrl=%2F290%2F&classifyTitle=%E5%A5%B3%E6%80%A7%E5%90%91",
                    "title": "女性向",
                    "url": "http://xxx.xxx.xxx/290/"
                },
                {
                    "route": "anime://classify.anime.app?partUrl=%2F151%2F&classifyTitle=%E6%B3%A1%E9%9D%A2%E7%95%AA",
                    "title": "泡面番",
                    "url": "http://xxx.xxx.xxx/151/"
                }
            ],
            "cover": {
                "referer": "http://xxx.xxx.xxx/201901/",
                "actionUrl": "",
                "url": "http://xxx.xxx.xxx/comic/acg/2019/01/01/201901011170.jpg"
            },
            "describe": "动漫简介：咖啡厅Rainy Color的老板天见浩司的女儿天见裕子担任代理店长的故事。本季的视觉图也得到了公开，可以看到6位个性不同的萌妹们亲密靠在一起的样子，她们背后则是咖啡厅Rainy Color。",
            "episode": "12集全",
            "route": "/show/4363.html",
            "title": "雨色可可第五季",
            "url": "http://xxx.xxx.xxx/show/4363.html"
        },
        {
            "animeType": [
                {
                    "route": "anime://classify.anime.app?partUrl=%2F91%2F&classifyTitle=%E6%81%8B%E7%88%B1",
                    "title": "恋爱",
                    "url": "http://xxx.xxx.xxx/91/"
                },
                {
                    "route": "anime://classify.anime.app?partUrl=%2F70%2F&classifyTitle=%E6%A0%A1%E5%9B%AD",
                    "title": "校园",
                    "url": "http://xxx.xxx.xxx/70/"
                },
                {
                    "route": "anime://classify.anime.app?partUrl=%2F151%2F&classifyTitle=%E6%B3%A1%E9%9D%A2%E7%95%AA",
                    "title": "泡面番",
                    "url": "http://xxx.xxx.xxx/151/"
                }
            ],
            "cover": {
                "referer": "http://xxx.xxx.xxx/201901/",
                "actionUrl": "",
                "url": "http://xxx.xxx.xxx/comic/acg/2019/01/01/201901011147.jpg"
            },
            "describe": "动漫简介：高中三年级的筒井光是所谓的御宅族少年。只要有游戏或动画里的二次元女生的话，感觉就能独自一人生活了……但是，他突然被超绝3D（现实）美少女·五十岚色叶告白，并开始了和她的交往！在被奔放的色叶玩弄于股掌...",
            "episode": "12集全",
            "route": "/show/4340.html",
            "title": "3D彼女第二季",
            "url": "http://xxx.xxx.xxx/show/4340.html"
        },
        {
            "animeType": [
                {
                    "route": "anime://classify.anime.app?partUrl=%2F70%2F&classifyTitle=%E6%A0%A1%E5%9B%AD",
                    "title": "校园",
                    "url": "http://xxx.xxx.xxx/70/"
                },
                {
                    "route": "anime://classify.anime.app?partUrl=%2F62%2F&classifyTitle=%E7%AB%9E%E6%8A%80",
                    "title": "竞技",
                    "url": "http://xxx.xxx.xxx/62/"
                },
                {
                    "route": "anime://classify.anime.app?partUrl=%2F77%2F&classifyTitle=%E5%89%A7%E6%83%85",
                    "title": "剧情",
                    "url": "http://xxx.xxx.xxx/77/"
                }
            ],
            "cover": {
                "referer": "http://xxx.xxx.xxx/201901/",
                "actionUrl": "",
                "url": "http://xxx.xxx.xxx/comic/acg/2019/01/01/20190101501.jpg"
            },
            "describe": "动漫简介：私立百花王学园表面为普通的名门学校，但实际上是以赌博决定学生排位的规定来支配的学园。铃井凉太受到班里赌博最强的早乙女芽亚里如畜牲般的对待，在外表美丽但内心却是对背负风险乐在其中的“赌博狂人”的美少...",
            "episode": "12集全",
            "route": "/show/4370.html",
            "title": "狂赌之渊第二季",
            "url": "http://xxx.xxx.xxx/show/4370.html"
        },
        {
            "animeType": [
                {
                    "route": "anime://classify.anime.app?partUrl=%2F75%2F&classifyTitle=%E7%A7%91%E5%B9%BB",
                    "title": "科幻",
                    "url": "http://xxx.xxx.xxx/75/"
                },
                {
                    "route": "anime://classify.anime.app?partUrl=%2F62%2F&classifyTitle=%E7%AB%9E%E6%8A%80",
                    "title": "竞技",
                    "url": "http://xxx.xxx.xxx/62/"
                },
                {
                    "route": "anime://classify.anime.app?partUrl=%2F70%2F&classifyTitle=%E6%A0%A1%E5%9B%AD",
                    "title": "校园",
                    "url": "http://xxx.xxx.xxx/70/"
                }
            ],
            "cover": {
                "referer": "http://xxx.xxx.xxx/201901/",
                "actionUrl": "",
                "url": "http://xxx.xxx.xxx/comic/acg/2019/01/01/201901011169.jpg"
            },
            "describe": "动漫简介：随着AR技术的发展，一项技术被研发成功，其名为混合现实系统，简称MR系统。使用MR进行的校园虚拟战斗“Circlet Bout”作为一项运动在女高中生中流行开来。这项运动的人气甚至冲破了学园，热潮席卷了各地，明星选...",
            "episode": "12集全",
            "route": "/show/4362.html",
            "title": "CIRCLET PRINCESS",
            "url": "http://xxx.xxx.xxx/show/4362.html"
        },
        {
            "animeType": [
                {
                    "route": "anime://classify.anime.app?partUrl=%2F67%2F&classifyTitle=%E6%90%9E%E7%AC%91",
                    "title": "搞笑",
                    "url": "http://xxx.xxx.xxx/67/"
                }
            ],
            "cover": {
                "referer": "http://xxx.xxx.xxx/201901/",
                "actionUrl": "",
                "url": "http://xxx.xxx.xxx/comic/acg/2019/01/01/201901011146.jpg"
            },
            "describe": "动漫简介：怕生的御宅族女大学生宫子，遇到了天使般的小学生！？在看到妹妹带来的新朋友小花的瞬间，宫子就无法抑制住心跳！！她为了和小花成为朋友而奋斗，但……“想要和超绝可爱的她做朋友”系小品喜剧，开幕♪",
            "episode": "13集全",
            "route": "/show/4339.html",
            "title": "天使降临到了我身边",
            "url": "http://xxx.xxx.xxx/show/4339.html"
        },
        {
            "animeType": [
                {
                    "route": "anime://classify.anime.app?partUrl=%2F72%2F&classifyTitle=%E7%BE%8E%E5%B0%91%E5%A5%B3",
                    "title": "美少女",
                    "url": "http://xxx.xxx.xxx/72/"
                },
                {
                    "route": "anime://classify.anime.app?partUrl=%2F73%2F&classifyTitle=%E9%AD%94%E6%B3%95",
                    "title": "魔法",
                    "url": "http://xxx.xxx.xxx/73/"
                }
            ],
            "cover": {
                "referer": "http://xxx.xxx.xxx/201901/",
                "actionUrl": "",
                "url": "http://xxx.xxx.xxx/comic/acg/2019/01/01/201901011140.jpg"
            },
            "describe": "动漫简介：曾经被称为宅文化圣地的秋叶原现在却成了办公街，动画和漫画的记忆逐渐被人们遗忘，动漫专门店逐渐关闭，数量越来越少。能够给与作品世界支持的是人们心中对作品的“回忆”。但是“病毒”破坏了作品世界，使得大...",
            "episode": "12集全",
            "route": "/show/4333.html",
            "title": "粉彩回忆",
            "url": "http://xxx.xxx.xxx/show/4333.html"
        },
        {
            "animeType": [
                {
                    "route": "anime://classify.anime.app?partUrl=%2F73%2F&classifyTitle=%E9%AD%94%E6%B3%95",
                    "title": "魔法",
                    "url": "http://xxx.xxx.xxx/73/"
                },
                {
                    "route": "anime://classify.anime.app?partUrl=%2F149%2F&classifyTitle=%E6%88%98%E6%96%97",
                    "title": "战斗",
                    "url": "http://xxx.xxx.xxx/149/"
                },
                {
                    "route": "anime://classify.anime.app?partUrl=%2F70%2F&classifyTitle=%E6%A0%A1%E5%9B%AD",
                    "title": "校园",
                    "url": "http://xxx.xxx.xxx/70/"
                }
            ],
            "cover": {
                "referer": "http://xxx.xxx.xxx/201901/",
                "actionUrl": "",
                "url": "http://xxx.xxx.xxx/comic/acg/2019/01/01/201901011157.jpg"
            },
            "describe": "动漫简介：「玛娜利亚的公主」是社交游戏「巴哈姆特之怒」的游戏内活动，于2015年8月决定将在2016年内制作电视动画版。 但本作和此前的动画除世界观相同外，没有什么联系，所以并不是其续作，而是更符合游戏的正统剧情。 由...",
            "episode": "10集全",
            "route": "/show/4350.html",
            "title": "玛娜利亚魔法学院",
            "url": "http://xxx.xxx.xxx/show/4350.html"
        },
        {
            "animeType": [
                {
                    "route": "anime://classify.anime.app?partUrl=%2F91%2F&classifyTitle=%E6%81%8B%E7%88%B1",
                    "title": "恋爱",
                    "url": "http://xxx.xxx.xxx/91/"
                },
                {
                    "route": "anime://classify.anime.app?partUrl=%2F70%2F&classifyTitle=%E6%A0%A1%E5%9B%AD",
                    "title": "校园",
                    "url": "http://xxx.xxx.xxx/70/"
                }
            ],
            "cover": {
                "referer": "http://xxx.xxx.xxx/201901/",
                "actionUrl": "",
                "url": "http://xxx.xxx.xxx/comic/acg/2019/01/01/201901011142.jpg"
            },
            "describe": "动漫简介：身为科学部部长的主人公上野，为了向自己喜欢的后辈田中传达出自己的心意，而使用各种自己的发明品进行超乎寻常的笨拙告白的内容。虽然上野的作战基本上都是以失败告终，但偶尔也能取得意外的进展。",
            "episode": "12集全",
            "route": "/show/4335.html",
            "title": "笨拙之极的上野",
            "url": "http://xxx.xxx.xxx/show/4335.html"
        },
        {
            "animeType": [
                {
                    "route": "anime://classify.anime.app?partUrl=%2F149%2F&classifyTitle=%E6%88%98%E6%96%97",
                    "title": "战斗",
                    "url": "http://xxx.xxx.xxx/149/"
                },
                {
                    "route": "anime://classify.anime.app?partUrl=%2F358%2F&classifyTitle=%E9%AD%94%E5%B9%BB",
                    "title": "魔幻",
                    "url": "http://xxx.xxx.xxx/358/"
                }
            ],
            "cover": {
                "referer": "http://xxx.xxx.xxx/201901/",
                "actionUrl": "",
                "url": "http://xxx.xxx.xxx/comic/acg/2019/01/01/201901011160.jpg"
            },
            "describe": "动漫简介：在某个距离地球非常遥远的星球上，有一个充满笑容的王国。十二岁的公主优希，正步入多愁善感的年纪。每天哭泣、欢笑、时而心动…？的同时，在王宫中快乐地度日。她忠实的家臣们，为她的每一天点缀色彩。负责教育...",
            "episode": "12集全",
            "route": "/show/4353.html",
            "title": "笑容的代价",
            "url": "http://xxx.xxx.xxx/show/4353.html"
        },
        {
            "animeType": [
                {
                    "route": "anime://classify.anime.app?partUrl=%2F151%2F&classifyTitle=%E6%B3%A1%E9%9D%A2%E7%95%AA",
                    "title": "泡面番",
                    "url": "http://xxx.xxx.xxx/151/"
                }
            ],
            "cover": {
                "referer": "http://xxx.xxx.xxx/201901/",
                "actionUrl": "",
                "url": "http://xxx.xxx.xxx/comic/acg/2019/01/01/201901011141.jpg"
            },
            "describe": "动漫简介：少女们的日常，时而战斗，时而不战斗？TV动画《刀使之巫女》与手机游戏《刀使之巫女刻印一闪之灯火》的角色们变身迷你版大集合！",
            "episode": "更新至12集",
            "route": "/show/4334.html",
            "title": "迷你刀使",
            "url": "http://xxx.xxx.xxx/show/4334.html"
        },
        {
            "animeType": [
                {
                    "route": "anime://classify.anime.app?partUrl=%2F64%2F&classifyTitle=%E6%A0%BC%E6%96%97",
                    "title": "格斗",
                    "url": "http://xxx.xxx.xxx/64/"
                },
                {
                    "route": "anime://classify.anime.app?partUrl=%2F72%2F&classifyTitle=%E7%BE%8E%E5%B0%91%E5%A5%B3",
                    "title": "美少女",
                    "url": "http://xxx.xxx.xxx/72/"
                },
                {
                    "route": "anime://classify.anime.app?partUrl=%2F70%2F&classifyTitle=%E6%A0%A1%E5%9B%AD",
                    "title": "校园",
                    "url": "http://xxx.xxx.xxx/70/"
                }
            ],
            "cover": {
                "referer": "http://xxx.xxx.xxx/201901/",
                "actionUrl": "",
                "url": "http://xxx.xxx.xxx/comic/acg/2019/01/01/201901011137.jpg"
            },
            "describe": "动漫简介：封印着三国时代，无法完成统一中华理想的英雄魂魄的勾玉流落到日本，并散落各地。勾玉具有着引导出继承者极限能力的力量，而被勾玉选中的人称之为“斗士”。为了追求天下第一强的封号，诸位继承者展开了永无止尽...",
            "episode": "3集全",
            "route": "/show/4330.html",
            "title": "一骑当千 Western Wolves",
            "url": "http://xxx.xxx.xxx/show/4330.html"
        },
        {
            "animeType": [
                {
                    "route": "anime://classify.anime.app?partUrl=%2F75%2F&classifyTitle=%E7%A7%91%E5%B9%BB",
                    "title": "科幻",
                    "url": "http://xxx.xxx.xxx/75/"
                },
                {
                    "route": "anime://classify.anime.app?partUrl=%2F61%2F&classifyTitle=%E5%86%92%E9%99%A9",
                    "title": "冒险",
                    "url": "http://xxx.xxx.xxx/61/"
                },
                {
                    "route": "anime://classify.anime.app?partUrl=%2F86%2F&classifyTitle=%E7%A9%BF%E8%B6%8A",
                    "title": "穿越",
                    "url": "http://xxx.xxx.xxx/86/"
                }
            ],
            "cover": {
                "referer": "http://xxx.xxx.xxx/201901/",
                "actionUrl": "",
                "url": "http://xxx.xxx.xxx/comic/acg/2019/01/01/201901011145.jpg"
            },
            "describe": "动漫简介：“这是预言。一个巨大的危机，将会降临到你们五人的身上。到那时候能保护他们的只有你了。”小时候曾经历过被人诱拐的高中二年级生堂岛大介，与儿时玩伴的凯、露、爱铃爱铃、庆作一起，被卷入了不可思议的现象“...",
            "episode": "12集全",
            "route": "/show/4338.html",
            "title": "Revisions",
            "url": "http://xxx.xxx.xxx/show/4338.html"
        },
        {
            "animeType": [
                {
                    "route": "anime://classify.anime.app?partUrl=%2F61%2F&classifyTitle=%E5%86%92%E9%99%A9",
                    "title": "冒险",
                    "url": "http://xxx.xxx.xxx/61/"
                },
                {
                    "route": "anime://classify.anime.app?partUrl=%2F75%2F&classifyTitle=%E7%A7%91%E5%B9%BB",
                    "title": "科幻",
                    "url": "http://xxx.xxx.xxx/75/"
                }
            ],
            "cover": {
                "referer": "http://xxx.xxx.xxx/201901/",
                "actionUrl": "",
                "url": "http://xxx.xxx.xxx/comic/acg/2019/01/01/201901011148.jpg"
            },
            "describe": "动漫简介：在补习中的男高中生们，意外的跨越次元穿越到了动画的世界当中，开始了他们的学园奇幻冒险——",
            "episode": "",
            "route": "/show/4341.html",
            "title": "Dimension High School",
            "url": "http://xxx.xxx.xxx/show/4341.html"
        },
        {
            "animeType": [
                {
                    "route": "anime://classify.anime.app?partUrl=%2F66%2F&classifyTitle=%E7%83%AD%E8%A1%80",
                    "title": "热血",
                    "url": "http://xxx.xxx.xxx/66/"
                }
            ],
            "cover": {
                "referer": "http://xxx.xxx.xxx/201901/",
                "actionUrl": "",
                "url": "http://xxx.xxx.xxx/comic/acg/2019/01/01/201901011139.jpg"
            },
            "describe": "动漫简介：“拳愿竞技”是企业、商人们赌上巨额利益，雇用斗技者并令其对打之空手格斗竞技。原为平息商人斗争之手段，始于江户中期，并传承至现代。 “乃木集团”庆安二年创业。以乃木商事为中心的企业集团。发展运输业、...",
            "episode": "",
            "route": "/show/4332.html",
            "title": "拳愿阿修罗",
            "url": "http://xxx.xxx.xxx/show/4332.html"
        }
    ]
}